plone.subrequest-2.0.6-py3.13-nspkg.pth
plone/subrequest/__init__.py
plone/subrequest/configure.zcml
plone/subrequest/interfaces.py
plone/subrequest/subresponse.py
plone/subrequest/testfile.txt
plone/subrequest/testing.py
plone/subrequest/testing.zcml
plone/subrequest/tests.py
plone/subrequest/usage.rst
plone_subrequest-2.0.6.dist-info/METADATA
plone_subrequest-2.0.6.dist-info/WHEEL
plone_subrequest-2.0.6.dist-info/entry_points.txt
plone_subrequest-2.0.6.dist-info/namespace_packages.txt
plone_subrequest-2.0.6.dist-info/top_level.txt
plone_subrequest-2.0.6.dist-info/RECORD
