Metadata-Version: 2.4
Name: plone.subrequest
Version: 2.0.6
Summary: Subrequests for Zope2
Home-page: https://github.com/plone/plone.subrequest
Author: Plone Foundation
Author-email: plone-developers@lists.sourceforge.net
License: GPL version 2
Keywords: plone
Platform: Any
Classifier: Development Status :: 5 - Production/Stable
Classifier: Environment :: Web Environment
Classifier: Framework :: Plone
Classifier: Framework :: Plone :: 6.0
Classifier: Framework :: Plone :: Core
Classifier: Framework :: Zope
Classifier: Framework :: Zope :: 5
Classifier: Intended Audience :: Developers
Classifier: License :: OSI Approved :: GNU General Public License v2 (GPLv2)
Classifier: Operating System :: OS Independent
Classifier: Programming Language :: Python
Classifier: Programming Language :: Python :: 3.8
Classifier: Programming Language :: Python :: 3.9
Classifier: Programming Language :: Python :: 3.10
Classifier: Programming Language :: Python :: 3.11
Requires-Python: >=3.8
Requires-Dist: setuptools
Requires-Dist: plone.protect
Requires-Dist: Zope
Provides-Extra: test
Requires-Dist: five.localsitemanager; extra == "test"
Requires-Dist: manuel; extra == "test"
Requires-Dist: plone.testing[zope]; extra == "test"
Requires-Dist: zope.configuration; extra == "test"
Dynamic: author
Dynamic: author-email
Dynamic: classifier
Dynamic: description
Dynamic: description-content-type
Dynamic: home-page
Dynamic: keywords
Dynamic: license
Dynamic: platform
Dynamic: provides-extra
Dynamic: requires-dist
Dynamic: requires-python
Dynamic: summary
